setup.py
sparse_dmd/__init__.py
sparse_dmd/sparse_dmd.py
sparse_dmd.egg-info/PKG-INFO
sparse_dmd.egg-info/SOURCES.txt
sparse_dmd.egg-info/dependency_links.txt
sparse_dmd.egg-info/top_level.txt