Metadata-Version: 1.0
Name: sparse-dmd
Version: 0.2
Summary: Sparse Dynamic Mode Decomposition
Home-page: http://github.com/aaren/sparse_dmd
Author: Aaron O'Leary
Author-email: eeaol@leeds.ac.uk
License: UNKNOWN
Platform: UNKNOWN
